ivy_memory/__init__.py
ivy_memory/geometric/__init__.py
ivy_memory/geometric/containers.py
ivy_memory/geometric/esm.py
ivy_memory/learnt/__init__.py
ivy_memory/learnt/ntm.py
ivy_memory-1.1.9.dist-info/LICENSE
ivy_memory-1.1.9.dist-info/METADATA
ivy_memory-1.1.9.dist-info/WHEEL
ivy_memory-1.1.9.dist-info/top_level.txt
ivy_memory-1.1.9.dist-info/RECORD
