Metadata-Version: 2.1
Name: ivy-memory
Version: 1.1.9
Summary: End-to-end memory modules for machine learning developers, written in Ivy.
Home-page: https://ivy-dl.org/memory
Author: Ivy Team
Author-email: ivydl.team@gmail.com
License: Apache 2.0
Project-URL: Docs, https://ivy-dl.org/memory/
Project-URL: Source, https://github.com/ivy-dl/memory
Platform: UNKNOWN
Classifier: License :: OSI Approved :: Apache Software License
License-File: LICENSE
Requires-Dist: ivy-core
Requires-Dist: ivy-mech
Requires-Dist: ivy-vision
